two_lists_similarity.py
two_lists_similarity-0.0.5.dist-info/LICENSE.txt
two_lists_similarity-0.0.5.dist-info/METADATA
two_lists_similarity-0.0.5.dist-info/WHEEL
two_lists_similarity-0.0.5.dist-info/top_level.txt
two_lists_similarity-0.0.5.dist-info/RECORD
