Metadata-Version: 2.1
Name: two-lists-similarity
Version: 0.0.5
Summary: A package to implement fuzzy matching between items in two different lists (an input list and a reference list.) 
Home-page: UNKNOWN
Author: Praneeth Ponnekanti
Author-email: praneeth.ponnekanti@gmail.com
License: UNKNOWN
Platform: UNKNOWN
Classifier: Programming Language :: Python :: 3
Classifier: License :: OSI Approved :: MIT License
Classifier: Operating System :: OS Independent
Requires-Python: >=3.6
